pythonwebtools/__init__.py
pythonwebtools/services/CryptService.py
pythonwebtools/services/HashService.py
pythonwebtools/services/__init__.py
pythonwebtools/utils/ValidatorUtils.py
pythonwebtools/utils/__init__.py
pythonwebtools-0.1.9.dist-info/LICENSE
pythonwebtools-0.1.9.dist-info/METADATA
pythonwebtools-0.1.9.dist-info/WHEEL
pythonwebtools-0.1.9.dist-info/top_level.txt
pythonwebtools-0.1.9.dist-info/RECORD
